pyradise/__init__.py
pyradise/__version__.py
pyradise/utils.py
pyradise/data/__init__.py
pyradise/data/annotator.py
pyradise/data/image.py
pyradise/data/modality.py
pyradise/data/organ.py
pyradise/data/subject.py
pyradise/data/taping.py
pyradise/data/utils.py
pyradise/fileio/__init__.py
pyradise/fileio/crawling.py
pyradise/fileio/dicom_conversion.py
pyradise/fileio/extraction.py
pyradise/fileio/loading.py
pyradise/fileio/modality_config.py
pyradise/fileio/selection.py
pyradise/fileio/series_info.py
pyradise/fileio/writing.py
pyradise/process/__init__.py
pyradise/process/base.py
pyradise/process/inference.py
pyradise/process/intensity.py
pyradise/process/invertibility.py
pyradise/process/modification.py
pyradise/process/orientation.py
pyradise/process/postprocess.py
pyradise/process/registration.py
pyradise/process/resampling.py
pyradise-0.2.3.dist-info/LICENSE
pyradise-0.2.3.dist-info/METADATA
pyradise-0.2.3.dist-info/WHEEL
pyradise-0.2.3.dist-info/top_level.txt
pyradise-0.2.3.dist-info/RECORD
