Metadata-Version: 2.1
Name: pyradise
Version: 0.2.3
Summary: PyRaDiSe: A Python package for DICOM-RT-based auto-segmentation pipeline construction and DICOM-RT data conversion
Home-page: https://pyradise.readthedocs.io/
Author: Elias Ruefenacht
Author-email: Elias Ruefenacht <elias.ruefenacht@unibe.ch>
License: Apache-2.0
Project-URL: Homepage, https://pyradise.readthedocs.io/
Project-URL: Bug Tracker, https://github.com/ubern-mia/pyradise/issues
Project-URL: GitHub, https://github.com/ubern-mia/pyradise/
Keywords: medical image analysis,deep learning,auto-segmentation,radiotherapy,DICOM conversion,DICOM data handling,DICOM-RT Structure Sets
Classifier: Development Status :: 3 - Alpha
Classifier: Intended Audience :: Developers
Classifier: Intended Audience :: Science/Research
Classifier: License :: OSI Approved :: Apache Software License
Classifier: Natural Language :: English
Classifier: Programming Language :: Python :: 3.8
Classifier: Programming Language :: Python :: 3.9
Classifier: Programming Language :: Python :: 3.10
Classifier: Programming Language :: Python :: 3.11
Classifier: Topic :: Scientific/Engineering :: Image Recognition
Classifier: Topic :: Scientific/Engineering :: Mathematics
Classifier: Topic :: Scientific/Engineering :: Medical Science Apps.
Classifier: Topic :: Software Development :: Libraries :: Python Modules
Classifier: Topic :: Software Development :: Libraries
Requires-Python: >=3.8
License-File: LICENSE
Requires-Dist: pydicom
Requires-Dist: numpy
Requires-Dist: itk (>=5.3)
Requires-Dist: SimpleITK
Requires-Dist: opencv-python
Requires-Dist: scipy
Requires-Dist: vtk
